pyModbusTCPtools/__init__.py
pyModbusTCPtools/enums.py
pyModbusTCPtools/exceptions.py
pyModbusTCPtools/modbustools.py
pymodbustcptools-0.1.0.dist-info/licenses/LICENSE
pymodbustcptools-0.1.0.dist-info/METADATA
pymodbustcptools-0.1.0.dist-info/WHEEL
pymodbustcptools-0.1.0.dist-info/top_level.txt
pymodbustcptools-0.1.0.dist-info/RECORD
