Metadata-Version: 2.4
Name: pyModbusTCPtools
Version: 0.1.0
Summary: Cliente Modbus TCP resiliente com leitura e escrita tipada, reconexão automática e endianness avançado
Author-email: Jocivaldo Siqueira da Silva Júnior <siqueira89jr@gmail.com>
License: MIT
Requires-Python: >=3.8
License-File: LICENSE
Requires-Dist: pyModbusTCP>=0.2.0
Dynamic: license-file
